pspec_likelihood/__init__.py
pspec_likelihood/arbitrary_linear_systematics.py
pspec_likelihood/likelihood.py
pspec_likelihood/types.py
pspec_likelihood/utils.py
pspec_likelihood/data/pspec_sim.h5
pspec_likelihood-0.2.0.dist-info/LICENSE
pspec_likelihood-0.2.0.dist-info/METADATA
pspec_likelihood-0.2.0.dist-info/WHEEL
pspec_likelihood-0.2.0.dist-info/top_level.txt
pspec_likelihood-0.2.0.dist-info/RECORD
