Metadata-Version: 2.1
Name: pspec-likelihood
Version: 0.2.0
Summary: A likelihood based on UVPSpec objects
Home-page: https://github.com/hera-team/pspec_likelihood
Author: HERA-Team
License: mit
Project-URL: Documentation, https://pspec_likelihood.readthedocs.org
Platform: any
Classifier: Development Status :: 1 - Planning
Classifier: Programming Language :: Python :: 3.8
Classifier: Programming Language :: Python :: 3.9
Classifier: Programming Language :: Python :: 3.10
Classifier: Programming Language :: Python :: 3.11
Classifier: Intended Audience :: Science/Research
Classifier: License :: OSI Approved
Classifier: License :: OSI Approved :: MIT License
Classifier: Natural Language :: English
Classifier: Topic :: Scientific/Engineering :: Physics
Classifier: Topic :: Scientific/Engineering :: Astronomy
License-File: LICENSE
Requires-Dist: hera-pspec
Requires-Dist: hera-sim
Requires-Dist: pyuvdata
Requires-Dist: attrs
Requires-Dist: cached-property
Provides-Extra: dev
Requires-Dist: pspec-likelihood[docs,tests] ; extra == 'dev'
Requires-Dist: setuptools-scm ; extra == 'dev'
Provides-Extra: docs
Requires-Dist: Sphinx (>=1.7.5) ; extra == 'docs'
Requires-Dist: numpydoc (>=0.8.0) ; extra == 'docs'
Requires-Dist: nbsphinx ; extra == 'docs'
Requires-Dist: sphinx-rtd-theme ; extra == 'docs'
Provides-Extra: tests
Requires-Dist: coverage (>=4.5.1) ; extra == 'tests'
Requires-Dist: pytest (>=3.5.1) ; extra == 'tests'
Requires-Dist: pytest-cov (>=2.5.1) ; extra == 'tests'
Requires-Dist: pre-commit ; extra == 'tests'
